pycloudsqlproxy/__init__.py
pycloudsqlproxy/cloud_sql_proxy
pycloudsqlproxy-0.0.15.dist-info/METADATA
pycloudsqlproxy-0.0.15.dist-info/WHEEL
pycloudsqlproxy-0.0.15.dist-info/top_level.txt
pycloudsqlproxy-0.0.15.dist-info/RECORD
