Metadata-Version: 2.1
Name: pycloudsqlproxy
Version: 0.0.15
Summary: Connect through cloud_sql_proxy
Home-page: http://github.com/noah-goodrich/pycloudsqlproxy
Author: Noah Goodrich
Author-email: me@noahgoodrich.com
License: Apache 2.0
Platform: UNKNOWN
